 [
	{
		"title":"Tom Petty/Mojo Album 300 x 250 Expandable w/video.",
		"image":"tomPetty2.jpg",
		"tools":"Adobe Flash(ActionScript2), Photoshop, AdWonder",
		"url":"http://apps.eyewonderlabs.com/adWdrVideoSpace/ad/108501/approvalJSTags.html"
    },
	{
		"title":"Tom Petty/Mojo Album 300 x 250 non-Expandable",
		"image":"tomPetty1.jpg",
		"tools":"Adobe Flash(ActionScript2), Photoshop, AdWonder",
		"url":"http://apps.eyewonderlabs.com/adWdrVideoSpace/ad/108497/approvalJSTags.html"
	},
	{
		"title":"American Heart Association Partners Recruit, 160x60",
		"image":"aha_160x60_partners.jpg",
		"tools":"Adobe Flash(ActionScript2), Photoshop",
		"url":"http://katomonster.com/aha160x600Partners"
	},
	{
		"title":"American Heart Association Teens Recruit, 728x90",
		"image":"aha728x90teens.jpg",
		"tools":"Adobe Flash(ActionScript2), Photoshop",
		"url":"http://katomonster.com/aha728x90Teens"
	},
	{
		"title":"Game-X 728x90 banner",
		"image":"gameX1.jpg",
		"tools":"Adobe Flash(ActionScript2), Photoshop",
		"url":"http://katomonster.com/gameX728x90"
	},
	{
		"title":"Game-X 300x250 banner",
		"image":"gameX2.jpg",
		"tools":"Adobe Flash(ActionScript2), Photoshop",
		"url":"http://katomonster.com/gameX300x250"
	},
	{
		"title":"Roadblock ad: Rolling, the movie",
		"image":"roadblock.jpg",
		"tools":"Adobe Flash(ActionScript2), Photoshop",
		"url":"http://katomonster.com/roadblock/roadblock.html"
	}
]